antipetros_discordbot/README.md
antipetros_discordbot/__init__.py
antipetros_discordbot/__main__.py
antipetros_discordbot/abstracts/README.md
antipetros_discordbot/abstracts/__init__.py
antipetros_discordbot/abstracts/connect_signal.py
antipetros_discordbot/abstracts/database_serializeable.py
antipetros_discordbot/abstracts/reaction_instruction_abstract.py
antipetros_discordbot/abstracts/subsupport_abstract.py
antipetros_discordbot/auxiliary_classes/README.md
antipetros_discordbot/auxiliary_classes/__init__.py
antipetros_discordbot/auxiliary_classes/all_item.py
antipetros_discordbot/auxiliary_classes/asking_items.py
antipetros_discordbot/auxiliary_classes/embed_handling.py
antipetros_discordbot/auxiliary_classes/hashed_message.py
antipetros_discordbot/auxiliary_classes/json_lists.py
antipetros_discordbot/auxiliary_classes/listener_object.py
antipetros_discordbot/auxiliary_classes/version_item.py
antipetros_discordbot/auxiliary_classes/voting_items.py
antipetros_discordbot/auxiliary_classes/aux_server_classes/__init__.py
antipetros_discordbot/auxiliary_classes/aux_server_classes/helper.py
antipetros_discordbot/auxiliary_classes/aux_server_classes/is_online_message_items.py
antipetros_discordbot/auxiliary_classes/aux_server_classes/server_item.py
antipetros_discordbot/auxiliary_classes/for_cogs/__init__.py
antipetros_discordbot/auxiliary_classes/for_cogs/aux_config_cog.py
antipetros_discordbot/auxiliary_classes/for_cogs/aux_faq_cog.py
antipetros_discordbot/auxiliary_classes/for_cogs/aux_give_away_cog.py
antipetros_discordbot/bot_support/__init__.py
antipetros_discordbot/bot_support/bot_supporter.py
antipetros_discordbot/bot_support/sub_support/__init__.py
antipetros_discordbot/bot_support/sub_support/antistasi_informer.py
antipetros_discordbot/bot_support/sub_support/blacklist_warden.py
antipetros_discordbot/bot_support/sub_support/chan_statistician.py
antipetros_discordbot/bot_support/sub_support/color_keeper.py
antipetros_discordbot-2.1.4.dist-info/entry_points.txt
antipetros_discordbot-2.1.4.dist-info/LICENSE
antipetros_discordbot-2.1.4.dist-info/WHEEL
antipetros_discordbot-2.1.4.dist-info/METADATA
antipetros_discordbot-2.1.4.dist-info/RECORD
