Metadata-Version: 2.1
Name: antipetros_discordbot
Version: 2.1.4
Summary: A Discord Bot for the Antistasi (ArmA 3) Community Discord Server
Home-page: https://github.com/Giddius/Antipetros_Discord_Bot
License: MIT
Author: antistasi_tools
Requires-Python: >=3.9
Classifier: License :: OSI Approved :: MIT License
Requires-Dist: Jinja2>=3.0.0
Requires-Dist: discord.py==1.7.1
Requires-Dist: Markdown==3.3.4
Requires-Dist: Pillow==8.2.0
Requires-Dist: PyGithub==1.54.1
Requires-Dist: Pygments==2.8.1
Requires-Dist: WeasyPrint==52.5
Requires-Dist: aiodav==0.1.4
Requires-Dist: aiohttp==3.7.4.post0
Requires-Dist: aiosqlite==0.17.0
Requires-Dist: antistasi_template_checker==0.1.1
Requires-Dist: arrow==1.0.3
Requires-Dist: async_property==0.2.1
Requires-Dist: asyncstdlib==3.9.1
Requires-Dist: beautifulsoup4==4.9.3
Requires-Dist: click==7.1.2
Requires-Dist: colormap==1.0.3
Requires-Dist: cryptography==3.4.7
Requires-Dist: dateparser==1.0.0
Requires-Dist: dpytest==0.0.23
Requires-Dist: emoji==1.2.0
Requires-Dist: ftfy==6.0.1
Requires-Dist: rapidfuzz==1.4.1
Requires-Dist: gidappdata==0.1.17
Requires-Dist: gidconfig==0.2.17
Requires-Dist: gidlogger==0.1.33
Requires-Dist: googletrans==4.0.0rc1
Requires-Dist: humanize==3.4.1
Requires-Dist: icecream==2.1.0
Requires-Dist: imgkit==1.2.2
Requires-Dist: inflect==5.3.0
Requires-Dist: marshmallow==3.11.1
Requires-Dist: matplotlib==3.4.1
Requires-Dist: natsort==7.1.1
Requires-Dist: psutil==5.8.0
Requires-Dist: pyfiglet==0.8.post1
Requires-Dist: pyparsing==2.4.7
Requires-Dist: python-youtube==0.8.1
Requires-Dist: python_a2s==1.3.0
Requires-Dist: python_dotenv
Requires-Dist: pytz==2021.1
Requires-Dist: rich==10.1.0
Requires-Dist: sortedcontainers==2.3.0
Requires-Dist: sqflint==0.3.2
Requires-Dist: validator_collection==1.5.0
Requires-Dist: watchgod==0.7
Requires-Dist: webdavclient3==3.14.5
Requires-Dist: discord-ext-ipc==2.0.0
Requires-Dist: discord-flags==2.1.1
Requires-Dist: discord-ext-ipc==2.0.0
Requires-Dist: easydev==0.11.0
Requires-Dist: yarl==1.6.3
Requires-Dist: scipy==1.7.0
